slack_bolt_router/__init__.py
slack_bolt_router/exceptions.py
slack_bolt_router/route_types.py
slack_bolt_router/router.py
slack_bolt_router/routers.py
slack_bolt_router-0.1.1.dist-info/LICENSE
slack_bolt_router-0.1.1.dist-info/WHEEL
slack_bolt_router-0.1.1.dist-info/METADATA
slack_bolt_router-0.1.1.dist-info/RECORD
