Metadata-Version: 2.1
Name: slack-bolt-router
Version: 0.1.1
Summary: Slack Bolt Router
Home-page: https://dmytrohoi.github.io/slack-bolt-router/
License: MIT
Keywords: slack,slack-bolt,slack-bolt plugin,slack-bolt router
Author: Dmytro Hoi
Author-email: code@dmytrohoi.com
Requires-Python: >=3.6,<4.0
Classifier: Development Status :: 4 - Beta
Classifier: License :: OSI Approved :: MIT License
Classifier: Operating System :: OS Independent
Classifier: Programming Language :: Python :: 3
Classifier: Programming Language :: Python :: 3.10
Classifier: Programming Language :: Python :: 3.6
Classifier: Programming Language :: Python :: 3.7
Classifier: Programming Language :: Python :: 3.8
Classifier: Programming Language :: Python :: 3.9
Classifier: Topic :: Communications
Classifier: Topic :: Communications :: Chat
Classifier: Topic :: Software Development
Classifier: Topic :: Utilities
Project-URL: Repository, https://github.com/dmytrohoi/slack-bolt-router/
